{
  "project_info": {
    "project_number": "268949892776",
    "project_id": "bloodbank-76707",
    "storage_bucket": "bloodbank-76707.appspot.com"
  },
  "client": [
    {
      "client_info": {
        "mobilesdk_app_id": "1:268949892776:android:2fa7932b59d44d53585c9d",
        "android_client_info": {
          "package_name": "com.example.blood_bank_management"
        }
      },
      "oauth_client": [],
      "api_key": [
        {
          "current_key": "AIzaSyDjyLHhZJrZfGrDicnIwwOR90AIWQdYdFM"
        }
      ],
      "services": {
        "appinvite_service": {
          "other_platform_oauth_client": []
        }
      }
    }
  ],
  "configuration_version": "1"
}